gitmaster/__init__.py
gitmaster/cli.py
gitmaster/config.py
gitmaster/main.py
gitmaster/pr_reviewer.py
gitmaster/auth/github.py
gitmaster/auth/keymanager.py
gitmaster/db/vector_store.py
gitmaster/embed/embedder.py
gitmaster/embed/splitter.py
gitmaster/loader/repo_loader.py
gitmaster/rag/agent.py
gitmaster/utils/logger.py
gitmaster/utils/network.py
gitmaster-0.1.4.dist-info/METADATA
gitmaster-0.1.4.dist-info/WHEEL
gitmaster-0.1.4.dist-info/entry_points.txt
gitmaster-0.1.4.dist-info/top_level.txt
gitmaster-0.1.4.dist-info/RECORD
