Metadata-Version: 2.4
Name: gitmaster
Version: 0.1.4
Summary: CLI tool to ask questions about GitHub or local repos using RAG + LLM
Author-email: Sayak Raha <sayakraha12@gmail.com>
Requires-Python: >=3.8
Requires-Dist: typer[all]
Requires-Dist: faiss-cpu
Requires-Dist: openai
Requires-Dist: tqdm
Requires-Dist: gitpython
Requires-Dist: openai
Requires-Dist: requests
Requires-Dist: keyring
Requires-Dist: python-dotenv
Requires-Dist: sentence-transformers
Requires-Dist: faiss-cpu
